{
    "Items": [
        {
            "_id": "chest.1",
            "_isUnlocked": false
        },
        {
            "_id": "chest.2",
            "_isUnlocked": false
        },
        {
            "_id": "chest.3",
            "_isUnlocked": false
        },
        {
            "_id": "chest.4",
            "_isUnlocked": false
        },
        {
            "_id": "hair.1",
            "_isUnlocked": false
        },
        {
            "_id": "hair.2",
            "_isUnlocked": false
        },
        {
            "_id": "hair.3",
            "_isUnlocked": false
        },
        {
            "_id": "Head.1",
            "_isUnlocked": false
        },
        {
            "_id": "Head.2",
            "_isUnlocked": false
        },
        {
            "_id": "Head.3",
            "_isUnlocked": false
        },
        {
            "_id": "Head.4",
            "_isUnlocked": false
        },
        {
            "_id": "Head.5",
            "_isUnlocked": false
        },
        {
            "_id": "Head.6",
            "_isUnlocked": false
        },
        {
            "_id": "pants.1",
            "_isUnlocked": false
        },
        {
            "_id": "pants.2",
            "_isUnlocked": false
        },
        {
            "_id": "pants.1",
            "_isUnlocked": false
        },
        {
            "_id": "shoes.1",
            "_isUnlocked": false
        },
        {
            "_id": "shoes.2",
            "_isUnlocked": false
        },
        {
            "_id": "shoes.3",
            "_isUnlocked": false
        },
        {
            "_id": "tail.1",
            "_isUnlocked": false
        },
        {
            "_id": "tail.2",
            "_isUnlocked": false
        },
        {
            "_id": "tail.3",
            "_isUnlocked": false
        },
        {
            "_id": "tail.4",
            "_isUnlocked": false
        },
        {
            "_id": "eyes.1",
            "_isUnlocked": false
        },
        {
            "_id": "eyes.2",
            "_isUnlocked": false
        },
        {
            "_id": "eyes.3",
            "_isUnlocked": false
        },
        {
            "_id": "eyes.4",
            "_isUnlocked": false
        },
        {
            "_id": "eyes.5",
            "_isUnlocked": false
        },
        {
            "_id": "eyes.6",
            "_isUnlocked": false
        },
        {
            "_id": "eyes.7",
            "_isUnlocked": false
        },
        {
            "_id": "eyes.8",
            "_isUnlocked": false
        },
        {
            "_id": "eyes.9",
            "_isUnlocked": false
        },
        {
            "_id": "skin.1",
            "_isUnlocked": false
        },
        {
            "_id": "skin.2",
            "_isUnlocked": false
        },
        {
            "_id": "skin.3",
            "_isUnlocked": false
        },
        {
            "_id": "skin.4",
            "_isUnlocked": false
        },
        {
            "_id": "skin.5",
            "_isUnlocked": false
        },
        {
            "_id": "skin.6",
            "_isUnlocked": false
        },
        {
            "_id": "skin.7",
            "_isUnlocked": false
        },
        {
            "_id": "skin.8",
            "_isUnlocked": false
        },
        {
            "_id": "skin.9",
            "_isUnlocked": false
        }
    ]
}